{
  "_review": {
    "status": "confirmed",
    "warnings": [
      "Dropped 1 non-scored row(s) worth 0 points (Penalty Points). Check they really aren't scored."
    ],
    "parsed_at": "2026-07-13T07:37:34.981Z",
    "prompt_version": "r-1.0.0",
    "source_pdf": "Marketing.pdf",
    "note": "Machine-parsed from the official rating sheet. plan.md F3: nobody may be graded against this until a human confirms it.",
    "confirmed_at": "2026-07-13T18:39:43.103Z",
    "confirmed_by": "ronit (bulk sign-off via scripts/confirm-rubrics.mts)",
    "paraphrased": true,
    "paraphrase_prompt_version": "p-1.0.0",
    "paraphrase_note": "Descriptions and level descriptors are restated in our own words (plan.md §20). Criterion names and every point value are exactly as published on the official rating sheet."
  },
  "title": "Marketing Role Play",
  "total_points": 100,
  "criteria": [
    {
      "id": "demonstrates_understanding_of_role_play",
      "name": "Demonstrates understanding of the role play and defines problem(s) to be solved",
      "description": "",
      "max_points": 10,
      "levels": [
        {
          "label": "Not Demonstrated",
          "points": 0,
          "descriptor": "The role-play scenario or its summary is absent, and no issues are identified."
        },
        {
          "label": "Below Expectations",
          "points": 6,
          "descriptor": "Either the role-play scenario and its summary are presented, or the core issues are identified."
        },
        {
          "label": "Meets Expectations",
          "points": 8,
          "descriptor": "The role-play scenario and its summary are presented, and the core issues are identified."
        },
        {
          "label": "Exceeds Expectations",
          "points": 10,
          "descriptor": "A thorough understanding of the role-play summary is evident, alongside a clear and precise definition of the problems."
        }
      ]
    },
    {
      "id": "identifies_alternatives_and_pros_cons",
      "name": "Identifies alternatives and the pro(s) and con(s) of each",
      "description": "",
      "max_points": 20,
      "levels": [
        {
          "label": "Not Demonstrated",
          "points": 0,
          "descriptor": "No potential solutions are put forward."
        },
        {
          "label": "Below Expectations",
          "points": 9,
          "descriptor": "Potential solutions are offered, but their advantages and/or disadvantages are not examined."
        },
        {
          "label": "Meets Expectations",
          "points": 16,
          "descriptor": "A minimum of two potential solutions are presented, with an analysis of their respective benefits and drawbacks."
        },
        {
          "label": "Exceeds Expectations",
          "points": 20,
          "descriptor": "Several potential solutions are presented, each with a comprehensive analysis of numerous advantages and disadvantages."
        }
      ]
    },
    {
      "id": "identifies_logical_solution_and_implemen",
      "name": "Identifies logical solution and aspects of implementation",
      "description": "",
      "max_points": 20,
      "levels": [
        {
          "label": "Not Demonstrated",
          "points": 0,
          "descriptor": "No proposed resolution is presented."
        },
        {
          "label": "Below Expectations",
          "points": 9,
          "descriptor": "A resolution is offered, but a strategy for putting it into practice is not outlined."
        },
        {
          "label": "Meets Expectations",
          "points": 16,
          "descriptor": "A sensible resolution is presented, along with a well-formed strategy for its execution."
        },
        {
          "label": "Exceeds Expectations",
          "points": 20,
          "descriptor": "A practical resolution and a detailed implementation strategy are developed, including the identification of required resources."
        }
      ]
    },
    {
      "id": "demonstrates_knowledge_of_event_areas",
      "name": "Demonstrates knowledge and understanding of the event knowledge areas",
      "description": "The core areas of knowledge for the event, which include Marketing Fundamentals, Market Planning, Marketing-Information Management, Product/Service Management, Channel Management, Pricing, Promotion, and Selling.",
      "max_points": 20,
      "levels": [
        {
          "label": "Not Demonstrated",
          "points": 0,
          "descriptor": "No understanding of the specified knowledge domains is shown."
        },
        {
          "label": "Below Expectations",
          "points": 9,
          "descriptor": "Understanding is shown in either one or two of the specified knowledge domains."
        },
        {
          "label": "Meets Expectations",
          "points": 16,
          "descriptor": "Understanding is shown in three of the specified knowledge domains."
        },
        {
          "label": "Exceeds Expectations",
          "points": 20,
          "descriptor": "Understanding is shown in four or more of the specified knowledge domains."
        }
      ]
    },
    {
      "id": "statements_well_organized_and_clearly_st",
      "name": "Statements are well-organized and clearly stated",
      "description": "",
      "max_points": 10,
      "levels": [
        {
          "label": "Not Demonstrated",
          "points": 0,
          "descriptor": "The competitor(s) did not appear ready."
        },
        {
          "label": "Below Expectations",
          "points": 6,
          "descriptor": "The competitor(s) were ready, but the presentation lacked a coherent structure."
        },
        {
          "label": "Meets Expectations",
          "points": 8,
          "descriptor": "The presentation progressed in a logical order."
        },
        {
          "label": "Exceeds Expectations",
          "points": 10,
          "descriptor": "The presentation progressed in a logical order, and all statements were clearly articulated and well-structured."
        }
      ]
    },
    {
      "id": "displays_confidence_body_language_eye_co",
      "name": "Consistently displays confidence, poised body language, engaging eye contact, and effective voice projection.",
      "description": "",
      "max_points": 10,
      "levels": [
        {
          "label": "Not Demonstrated",
          "points": 0,
          "descriptor": "None of the specified communication skills were exhibited."
        },
        {
          "label": "Below Expectations",
          "points": 6,
          "descriptor": "One or two of the specified communication skills (confidence, body language, eye contact, or voice projection) were exhibited."
        },
        {
          "label": "Meets Expectations",
          "points": 8,
          "descriptor": "Three of the specified communication skills (confidence, body language, eye contact, or voice projection) were exhibited."
        },
        {
          "label": "Exceeds Expectations",
          "points": 10,
          "descriptor": "All specified communication skills were exhibited, significantly enhancing the overall delivery."
        }
      ]
    },
    {
      "id": "demonstrates_ability_to_answer_questions",
      "name": "Demonstrates the ability to effectively answer questions",
      "description": "",
      "max_points": 10,
      "levels": [
        {
          "label": "Not Demonstrated",
          "points": 0,
          "descriptor": "Incapable of providing responses to inquiries."
        },
        {
          "label": "Below Expectations",
          "points": 6,
          "descriptor": "Responses to inquiries are incomplete."
        },
        {
          "label": "Meets Expectations",
          "points": 8,
          "descriptor": "Responses to inquiries are thorough and complete."
        },
        {
          "label": "Exceeds Expectations",
          "points": 10,
          "descriptor": "Engaged with the judges while providing comprehensive answers to inquiries."
        }
      ]
    }
  ]
}